comparefiles/__init__.py
comparefiles/compare_files.py
comparefiles/database_query.py
comparefiles/test/__init__.py
emwinCompareFiles-0.2.11.dist-info/LICENSE.txt
emwinCompareFiles-0.2.11.dist-info/METADATA
emwinCompareFiles-0.2.11.dist-info/WHEEL
emwinCompareFiles-0.2.11.dist-info/top_level.txt
emwinCompareFiles-0.2.11.dist-info/RECORD
