Metadata-Version: 2.1
Name: emwinCompareFiles
Version: 0.2.11
Summary: EMWIN Latency Comparison.
Home-page: http://pypi.org/project/emwinCompareFiles/
Author: Katie D'Adamo
Author-email: katherine.dadamo@noaa.gov
License: LICENSE.txt
Platform: UNKNOWN
Requires-Dist: Django (>=1.1)
Requires-Dist: caldav (==0.1.4)
